my_timesunion_sdk/__init__.py
my_timesunion_sdk/my_timesunion_sdk.py
my_timesunion_sdk-0.0.9.dist-info/LICENSE
my_timesunion_sdk-0.0.9.dist-info/METADATA
my_timesunion_sdk-0.0.9.dist-info/WHEEL
my_timesunion_sdk-0.0.9.dist-info/top_level.txt
my_timesunion_sdk-0.0.9.dist-info/RECORD
