Metadata-Version: 2.1
Name: my-timesunion-sdk
Version: 0.0.9
Summary: A commonly used tool library
Home-page: https://github.com/my-timesunion-sdk/
Author: xhh
Author-email: 380472213@qq.com
License: MIT
Keywords: my,times,union,sdk
Platform: UNKNOWN
License-File: LICENSE
Requires-Dist: requests
Requires-Dist: arrow
